{"@t":"2019-07-29T07:07:01.9950585Z","@mt":"Stopping ({SignalSource})","SignalSource":"signal","SourceContext":"Umbraco.Core.MainDom","ProcessId":19772,"ProcessName":"w3wp","ThreadId":235,"AppDomainId":42,"AppDomainAppId":"LMW3SVC7ROOT","MachineName":"DESKTOP-DHEDIOQ","Log4NetLevel":"INFO "}
{"@t":"2019-07-29T07:07:02.0593029Z","@mt":"{StartMessage} [Timing {TimingId}]","StartMessage":"Examine shutting down","TimingId":"4f88b52","SourceContext":"Umbraco.Web.Search.ExamineComponent","ProcessId":19772,"ProcessName":"w3wp","ThreadId":235,"AppDomainId":42,"AppDomainAppId":"LMW3SVC7ROOT","MachineName":"DESKTOP-DHEDIOQ","Log4NetLevel":"INFO "}
{"@t":"2019-07-29T07:07:02.0652851Z","@mt":"{EndMessage} ({Duration}ms) [Timing {TimingId}]","EndMessage":"Completed.","Duration":5,"TimingId":"4f88b52","SourceContext":"Umbraco.Web.Search.ExamineComponent","ProcessId":19772,"ProcessName":"w3wp","ThreadId":235,"AppDomainId":42,"AppDomainAppId":"LMW3SVC7ROOT","MachineName":"DESKTOP-DHEDIOQ","Log4NetLevel":"INFO "}
